crispy_tailwind/__init__.py
crispy_tailwind/layout.py
crispy_tailwind/tailwind.py
crispy_tailwind/templates/tailwind/display_form.html
crispy_tailwind/templates/tailwind/errors.html
crispy_tailwind/templates/tailwind/errors_formset.html
crispy_tailwind/templates/tailwind/field.html
crispy_tailwind/templates/tailwind/inputs.html
crispy_tailwind/templates/tailwind/table_inline_formset.html
crispy_tailwind/templates/tailwind/uni_form.html
crispy_tailwind/templates/tailwind/uni_formset.html
crispy_tailwind/templates/tailwind/whole_uni_form.html
crispy_tailwind/templates/tailwind/whole_uni_formset.html
crispy_tailwind/templates/tailwind/layout/alert.html
crispy_tailwind/templates/tailwind/layout/attrs.html
crispy_tailwind/templates/tailwind/layout/baseinput.html
crispy_tailwind/templates/tailwind/layout/button.html
crispy_tailwind/templates/tailwind/layout/buttonholder.html
crispy_tailwind/templates/tailwind/layout/checkboxselectmultiple.html
crispy_tailwind/templates/tailwind/layout/checkboxselectmultiple_inline.html
crispy_tailwind/templates/tailwind/layout/column.html
crispy_tailwind/templates/tailwind/layout/div.html
crispy_tailwind/templates/tailwind/layout/field_errors.html
crispy_tailwind/templates/tailwind/layout/field_errors_block.html
crispy_tailwind/templates/tailwind/layout/field_with_buttons.html
crispy_tailwind/templates/tailwind/layout/fieldset.html
crispy_tailwind/templates/tailwind/layout/formactions.html
crispy_tailwind/templates/tailwind/layout/help_text.html
crispy_tailwind/templates/tailwind/layout/help_text_and_errors.html
crispy_tailwind/templates/tailwind/layout/inline_field.html
crispy_tailwind/templates/tailwind/layout/prepended_appended_text.html
crispy_tailwind/templates/tailwind/layout/radioselect.html
crispy_tailwind/templates/tailwind/layout/radioselect_inline.html
crispy_tailwind/templates/tailwind/layout/row.html
crispy_tailwind/templates/tailwind/layout/select.html
crispy_tailwind/templates/tailwind/layout/select_option.html
crispy_tailwind-1.0.2.dist-info/LICENSE.txt
crispy_tailwind-1.0.2.dist-info/METADATA
crispy_tailwind-1.0.2.dist-info/WHEEL
crispy_tailwind-1.0.2.dist-info/top_level.txt
crispy_tailwind-1.0.2.dist-info/RECORD
