Metadata-Version: 2.1
Name: crispy-tailwind
Version: 1.0.2
Summary: Tailwind CSS for Django Crispy Forms
Author-email: David Smith <smithdc@gmail.com>
License: MIT
Project-URL: Homepage, https://github.com/django-crispy-forms/crispy-tailwind
Project-URL: Issues, https://github.com/django-crispy-forms/crispy-tailwind/issues
Project-URL: Changelog, https://github.com/django-crispy-forms/crispy-tailwind/releases
Classifier: Development Status :: 5 - Production/Stable
Classifier: Environment :: Web Environment
Classifier: Framework :: Django
Classifier: Framework :: Django :: 4.2
Classifier: Framework :: Django :: 5.0
Classifier: License :: OSI Approved :: MIT License
Classifier: Operating System :: OS Independent
Classifier: Programming Language :: JavaScript
Classifier: Programming Language :: Python :: 3
Classifier: Programming Language :: Python :: 3.8
Classifier: Programming Language :: Python :: 3.9
Classifier: Programming Language :: Python :: 3.10
Classifier: Programming Language :: Python :: 3.11
Classifier: Programming Language :: Python :: 3.12
Classifier: Topic :: Internet :: WWW/HTTP
Classifier: Topic :: Internet :: WWW/HTTP :: Dynamic Content
Classifier: Topic :: Software Development :: Libraries :: Python Modules
Requires-Python: >=3.8
License-File: LICENSE.txt
Requires-Dist: django-crispy-forms >=2.0
Requires-Dist: django >=4.2
Provides-Extra: test
Requires-Dist: pytest ; extra == 'test'
Requires-Dist: pytest-django ; extra == 'test'
